tailparse/__init__.py
tailparse/cli.py
tailparse/execute.py
tailparse/print_output.py
tailparse/log_formats/__init__.py
tailparse/log_formats/nginx.py
tailparse/tests/__init__.py
tailparse/tests/test_nginx.py
tailparse/tests/test_print_output.py
tailparse/tests/test_regexp_format.py
tailparse/tests/test_smoke.py
tailparse-0.2.dist-info/LICENSE
tailparse-0.2.dist-info/METADATA
tailparse-0.2.dist-info/WHEEL
tailparse-0.2.dist-info/entry_points.txt
tailparse-0.2.dist-info/top_level.txt
tailparse-0.2.dist-info/RECORD
