Metadata-Version: 2.1
Name: tailparse
Version: 0.2
Summary: Parser Nginx logs like SQL
Home-page: https://github.com/valexandersaulys/tailparse
Author: Vincent A. Saulys
Author-email: Vincent A Saulys <vincent@saulys.me>
Project-URL: Homepage, https://github.com/valexandersaulys/tailparse
Project-URL: Bug Tracker, https://github.com/valexandersaulys/tailparse/issues
Classifier: Programming Language :: Python :: 3
Classifier: Operating System :: OS Independent
Classifier: Development Status :: 4 - Beta
Classifier: License :: OSI Approved :: GNU General Public License v3 or later (GPLv3+)
Classifier: Topic :: Internet :: Log Analysis
Requires-Python: >=3.6
License-File: LICENSE
